[
  {
    "name": "administrator",
    "email": "a@gogogogo.com",
    "roleNames": ["Administrator", "Privileged", "Authenticated"],
    "online": false,
    "dateCreated": "2017-04-14T12:30:00.000Z",
    "dateModified": "2017-04-14T12:30:00.000Z"
  },
  {
    "name": "privileged",
    "email": "b@gogogogo.com",
    "roleNames": ["Privileged", "Authenticated"],
    "online": false,
    "dateCreated": "2017-04-14T12:30:00.000Z",
    "dateModified": "2017-04-14T12:30:00.000Z"
  },
  {
    "name": "authenticated",
    "email": "c@gogogogo.com",
    "roleNames": ["Authenticated"],
    "online": false,
    "dateCreated": "2017-04-14T12:30:00.000Z",
    "dateModified": "2017-04-14T12:30:00.000Z"
  }
]
